odoo9_addon_openeducat_admission-9.0.2.4.0-py2.7-nspkg.pth
odoo9_addon_openeducat_admission-9.0.2.4.0.dist-info/top_level.txt
odoo9_addon_openeducat_admission-9.0.2.4.0.dist-info/WHEEL
odoo9_addon_openeducat_admission-9.0.2.4.0.dist-info/RECORD
odoo9_addon_openeducat_admission-9.0.2.4.0.dist-info/metadata.json
odoo9_addon_openeducat_admission-9.0.2.4.0.dist-info/DESCRIPTION.rst
odoo9_addon_openeducat_admission-9.0.2.4.0.dist-info/METADATA
odoo9_addon_openeducat_admission-9.0.2.4.0.dist-info/namespace_packages.txt
odoo_addons/openeducat_admission/__openerp__.py
odoo_addons/openeducat_admission/admission_menu.xml
odoo_addons/openeducat_admission/__init__.py
odoo_addons/openeducat_admission/security/ir.model.access.csv
odoo_addons/openeducat_admission/report/report_admission_analysis.xml
odoo_addons/openeducat_admission/report/admission_analysis_report.py
odoo_addons/openeducat_admission/report/__init__.py
odoo_addons/openeducat_admission/report/report_menu.xml
odoo_addons/openeducat_admission/models/admission.py
odoo_addons/openeducat_admission/models/__init__.py
odoo_addons/openeducat_admission/models/admission_register.py
odoo_addons/openeducat_admission/i18n/openeducat_admission.pot
odoo_addons/openeducat_admission/wizard/admission_analysis_wizard.py
odoo_addons/openeducat_admission/wizard/admission_analysis_wizard_view.xml
odoo_addons/openeducat_admission/wizard/__init__.py
odoo_addons/openeducat_admission/views/admission_view.xml
odoo_addons/openeducat_admission/views/admission_register_view.xml
odoo_addons/openeducat_admission/views/admission_sequence.xml
odoo_addons/openeducat_admission/demo/op.admission.csv
odoo_addons/openeducat_admission/demo/product.product.csv
odoo_addons/openeducat_admission/demo/product.category.csv
odoo_addons/openeducat_admission/demo/student_demo.xml
odoo_addons/openeducat_admission/demo/op.admission.register.csv
odoo_addons/openeducat_admission/static/img/student_4.jpg
odoo_addons/openeducat_admission/static/img/student_11.jpg
odoo_addons/openeducat_admission/static/img/student_5.jpg
odoo_addons/openeducat_admission/static/img/student_16.jpg
odoo_addons/openeducat_admission/static/img/student_10.jpg
odoo_addons/openeducat_admission/static/img/student_13.jpg
odoo_addons/openeducat_admission/static/img/student_7.jpg
odoo_addons/openeducat_admission/static/img/student_17.jpg
odoo_addons/openeducat_admission/static/img/student_1.jpg
